{
  "id": "mdb-metadb-stats",
  "projectId": "{{projectId}}",
  "name": "MDB stats",
  "description": "",
  "heightMultiplier": 1,
  "parameters": [
      {
          "name": "cluster",
          "value": "<< metadb_cluster_name >>"
      },
      {
          "name": "service",
          "value": "<< metadb_service_id >>"
      },
      {
          "name": "project",
          "value": "{{projectId}}"
      }
  ],
  "rows": [
    {
      "panels": [
        {
          "type": "IFRAME",
          "title": "Hosts by flavor type",
          "subtitle": "",
          "url": "?cluster={{cluster}}&project={{project}}&service={{service}}&graph=cloud-mdb-metadb-hosts-by-flavor-type&hideNoData=true",
          "markdown": "",
          "rowspan": 0,
          "colspan": 0
        },
        {
          "type": "IFRAME",
          "title": "Hosts by flavor generation",
          "subtitle": "",
          "url": "?cluster={{cluster}}&project={{project}}&service={{service}}&graph=cloud-mdb-metadb-hosts-by-flavor-generation&hideNoData=true",
          "markdown": "",
          "rowspan": 0,
          "colspan": 0
        }
      ]
    },
    {
      "panels": [
        {
          "type": "IFRAME",
          "title": "Resource presets",
          "subtitle": "",
          "url": "?cluster={{cluster}}&project={{project}}&service={{service}}&graph=cloud-mdb-metadb-resource-presets&hideNoData=true",
          "markdown": "",
          "rowspan": 0,
          "colspan": 0
        },
        {
          "type": "IFRAME",
          "title": "Hosts by cluster type",
          "subtitle": "",
          "url": "?cluster={{cluster}}&project={{project}}&service={{service}}&graph=cloud-mdb-metadb-hosts-by-cluster-type&hideNoData=true",
          "markdown": "",
          "rowspan": 0,
          "colspan": 0
        }
      ]
    },
    {
      "panels": [
        {
          "type": "IFRAME",
          "title": "Clusters by status",
          "subtitle": "",
          "url": "?cluster={{cluster}}&project={{project}}&service={{service}}&graph=cloud-mdb-metadb-cluster-statuses&hideNoData=true",
          "markdown": "",
          "rowspan": 0,
          "colspan": 0
        },
        {
          "type": "IFRAME",
          "title": "Clusters by type",
          "subtitle": "",
          "url": "?cluster={{cluster}}&project={{project}}&service={{service}}&graph=cloud-mdb-metadb-cluster-types&hideNoData=true",
          "markdown": "",
          "rowspan": 0,
          "colspan": 0
        }
      ]
    },
    {
      "panels": [
        {
          "type": "IFRAME",
          "title": "PostgreSQL hosts count",
          "subtitle": "",
          "url": "?cluster={{cluster}}&project={{project}}&service={{service}}&graph=cloud-mdb-metadb-postgresql-hosts-count&hideNoData=true",
          "markdown": "",
          "rowspan": 0,
          "colspan": 0
        },
        {
          "type": "IFRAME",
          "title": "PostgreSQL space used",
          "subtitle": "",
          "url": "?cluster={{cluster}}&project={{project}}&service={{service}}&graph=cloud-mdb-metadb-postgresql-space-used&hideNoData=true",
          "markdown": "",
          "rowspan": 0,
          "colspan": 0
        }
      ]
    },
    {
      "panels": [
        {
          "type": "IFRAME",
          "title": "ClickHouse hosts count",
          "subtitle": "",
          "url": "?cluster={{cluster}}&project={{project}}&service={{service}}&graph=cloud-mdb-metadb-clickhouse-hosts-count&hideNoData=true",
          "markdown": "",
          "rowspan": 0,
          "colspan": 0
        },
        {
          "type": "IFRAME",
          "title": "ClickHouse space used",
          "subtitle": "",
          "url": "?cluster={{cluster}}&project={{project}}&service={{service}}&graph=cloud-mdb-metadb-clickhouse-space-used&hideNoData=true",
          "markdown": "",
          "rowspan": 0,
          "colspan": 0
        }
      ]
    },
    {
      "panels": [
        {
          "type": "IFRAME",
          "title": "MongoDB hosts count",
          "subtitle": "",
          "url": "?cluster={{cluster}}&project={{project}}&service={{service}}&graph=cloud-mdb-metadb-mongodb-hosts-count&hideNoData=true",
          "markdown": "",
          "rowspan": 0,
          "colspan": 0
        },
        {
          "type": "IFRAME",
          "title": "MongoDB space used",
          "subtitle": "",
          "url": "?cluster={{cluster}}&project={{project}}&service={{service}}&graph=cloud-mdb-metadb-mongodb-space-used&hideNoData=true",
          "markdown": "",
          "rowspan": 0,
          "colspan": 0
        }
      ]
    },
    {
      "panels": [
        {
          "type": "IFRAME",
          "title": "Redis hosts count",
          "subtitle": "",
          "url": "?cluster={{cluster}}&project={{project}}&service={{service}}&graph=cloud-mdb-metadb-redis-hosts-count&hideNoData=true",
          "markdown": "",
          "rowspan": 0,
          "colspan": 0
        },
        {
          "type": "IFRAME",
          "title": "Redis space used",
          "subtitle": "",
          "url": "?cluster={{cluster}}&project={{project}}&service={{service}}&graph=cloud-mdb-metadb-redis-space-used&hideNoData=true",
          "markdown": "",
          "rowspan": 0,
          "colspan": 0
        }
      ]
    },
    {
      "panels": [
        {
          "type": "IFRAME",
          "title": "MySQL hosts count",
          "subtitle": "",
          "url": "?cluster={{cluster}}&project={{project}}&service={{service}}&graph=cloud-mdb-metadb-mysql-hosts-count&hideNoData=true",
          "markdown": "",
          "rowspan": 0,
          "colspan": 0
        },
        {
          "type": "IFRAME",
          "title": "MySQL space used",
          "subtitle": "",
          "url": "?cluster={{cluster}}&project={{project}}&service={{service}}&graph=cloud-mdb-metadb-mysql-space-used&hideNoData=true",
          "markdown": "",
          "rowspan": 0,
          "colspan": 0
        }
      ]
    },
    {
      "panels": [
        {
          "type": "IFRAME",
          "title": "Dataproc hosts count",
          "subtitle": "",
          "url": "?cluster={{cluster}}&project={{project}}&service={{service}}&graph=cloud-mdb-metadb-dataproc-hosts-count&hideNoData=true",
          "markdown": "",
          "rowspan": 0,
          "colspan": 0
        },
        {
          "type": "IFRAME",
          "title": "Dataproc space used",
          "subtitle": "",
          "url": "?cluster={{cluster}}&project={{project}}&service={{service}}&graph=cloud-mdb-metadb-dataproc-space-used&hideNoData=true",
          "markdown": "",
          "rowspan": 0,
          "colspan": 0
        }
      ]
    }
  ],
  "createdAt": "2018-10-16T11:39:37.278Z",
  "updatedAt": "2019-05-22T07:05:35.775Z",
  "createdBy": "d0uble",
  "updatedBy": "asalimonov",
  "version": 22
}
