{
    "dcs": {
        "ugr": "Угрешка",
        "iva": "Ивантеевка",
        "fol": "Фольга",
        "sas": "Сасово",
        "man": "Мянтсяля",
        "vla": "Владимир"
    },
    "services": {
        "kp":       "КП",
        "tv":       "ТВ",
        "kino":     "Кино",
        "afisha":   "Афиша",
        "tickets":  "Билеты",
        "music":    "Музыка",
        "reserve":  "Резерв"
    },
    "usage": [
        { "dc": "iva", "service": "kp", "ram": 123, "cpu": 456, "usage": 75 },
        { "dc": "fol", "service": "kp", "ram": 23, "cpu": 756, "usage": 90 },
        { "dc": "sas", "service": "tv", "ram": 23, "cpu": 56, "usage": 90 },
        { "dc": "sas", "service": "kino", "ram": 23, "cpu": 56, "usage": 90 },
        { "dc": "sas", "service": "afisha", "ram": 23, "cpu": 56, "usage": 90 },
        { "dc": "sas", "service": "tickets", "ram": 23, "cpu": 56, "usage": 90 },
        { "dc": "sas", "service": "music", "ram": 23, "cpu": 56, "usage": 90 },
        { "dc": "sas", "service": "reserve", "ram": 23, "cpu": 56, "usage": 90 }
    ]
}
