[{
  "given":
  {
    "m_one": -1,
    "zero": 0,
    "one": 1,
    "two": 2,
    "ten": 10,
    "many": 123.45,
    "s_ten": "10",
    "s_five": "5",
    "true": true,
    "false": false
  },
  "cases": [
    {
      "expression": "add(one,two)",
      "result": 3
    },
    {
      "expression": "add(one,m_one)",
      "result": 0
    },
    {
      "expression": "add(many,ten)",
      "result": 133.45
    },
    {
      "expression": "add(true,false)",
      "error": "invalid-type"
    },
    {
      "expression": "add(s_ten,s_five)",
      "result": 15
    },
    {
      "expression": "add(ten,`null`)",
      "result": 10
    },
    {
      "expression": "mul(many,two)",
      "result": 246.9
    },
    {
      "expression": "mul(zero,ten)",
      "result": 0
    },
    {
      "expression": "mul(true,false)",
      "error": "invalid-type"
    },
    {
      "expression": "mul(s_ten,s_five)",
      "result": 50
    },
    {
      "expression": "mul(ten, `null`)",
      "result": 0
    },
    {
      "expression": "quantum(many,two)",
      "result": 124
    },
    {
      "expression": "quantum(zero,ten)",
      "result": 0
    },
    {
      "expression": "quantum(true,false)",
      "error": "invalid-type"
    },
    {
      "expression": "quantum(s_ten,s_five)",
      "result": 10
    },
    {
      "expression": "quantum(ten, `null`)",
      "result": null
    },
    {
      "expression": "hash_mod(s_ten, one)",
      "result": 0
    },
    {
      "expression": "hash_mod(s_five, two)",
      "result": 1
    },
    {
      "expression": "div(ten,two)",
      "result": 5
    },
    {
      "expression": "div(zero,ten)",
      "result": 0
    },
    {
      "expression": "div(ten,zero)",
      "result": null
    },
    {
      "expression": "div(true,false)",
      "error": "invalid-type"
    },
    {
      "expression": "div(s_ten,s_five)",
      "result": 2
    },
    {
      "expression": "div(ten, `null`)",
      "result": null
    },
    {
      "expression": "sub(two,one)",
      "result": 1
    },
    {
      "expression": "sub(one,m_one)",
      "result": 2
    },
    {
      "expression": "sub(many,ten)",
      "result": 113.45
    },
    {
      "expression": "sub(true,false)",
      "error": "invalid-type"
    },
    {
      "expression": "sub(s_ten,s_five)",
      "result": 5
    },
    {
      "expression": "sub(ten,`null`)",
      "result": 10
    },
    {
      "expression": "if(true, 't', 'f')",
      "result": "t"
    },
    {
      "expression": "if(false, 't', 'f')",
      "result": "f"
    },
    {
      "expression": "if(s_ten, 't', 'f')",
      "result": "t"
    },
    {
      "expression": "if(zero, 't', 'f')",
      "error": "invalid-type"
    }  ,
    {
      "expression": "decimal(one)",
      "result": 1
    },
    {
      "expression": "decimal(s_ten)",
      "result": 10
    },
    {
      "expression": "decimal(true)",
      "result": null
    }
  ]
}]
