{"norm_query": "\u043f\u0440\u0435\u0437\u0438\u0434\u0435\u043d\u0442 \u0443\u043a\u0440\u0430\u0438\u043d\u0430 __marker__", "base_info": {"entref": "0oCgZydXc3MzLynjXO", "title": "\u0423\u043a\u0440\u0430\u0438\u043d\u0430", "url": "http://ru.wikipedia.org/wiki/\u0423\u043a\u0440\u0430\u0438\u043d\u0430", "image": {"src": [{"url": "http://en.wikipedia.org/wiki/Ukraine", "value": "enw", "url_type": "page"}], "thumb": "Default", "color_wiz": {"text": "#D9E0CE", "button": "#92A775", "back": "#7F985D", "button_text": "#FFFFFF"}, "url": "http://upload.wikimedia.org/wikipedia/commons/thumb/4/49/Flag_of_Ukraine.svg/800px-Flag_of_Ukraine.svg.png", "value": "http://upload.wikimedia.org/wikipedia/commons/thumb/4/49/Flag_of_Ukraine.svg/800px-Flag_of_Ukraine.svg.png", "mark": ["10@ru"], "show_on_serp": true, "avatar_type": "flag", "faces_count": 0, "original_size": {"width": 800, "height": 533}, "mds_avatar_id": "61037/114912363", "type": "flag", "RelevLocale": ["universe"]}, "freqs": {"ontodb_panel_freq_30": 476608, "wikihits": 6883541, "sum_qf": 69119811, "ontodb_panel_freq": 3683132}, "search_request": "\u0423\u043a\u0440\u0430\u0438\u043d\u0430", "type": "Geo", "id": "ruw732"}, "url": null, "text": null, "counter": {"path": "/wiz/entity-fact", "vars": {"pos": "pimportant"}}, "voiceInfo": {"ru": [{"lang": "ru-RU", "text": "\u041f\u0451\u0442\u0440 \u0410\u043b\u0435\u043a\u0441\u0435\u0435\u0432\u0438\u0447 \u041f\u043e\u0440\u043e\u0448\u0435\u043d\u043a\u043e "}]}, "source": "object_facts", "requested_facts": {"item": [{"name": "\u0413\u043b\u0430\u0432\u044b", "value": [{"entref": "0oCglydXcyMTA1NTMYAmvE-LM", "text": "\u041f\u0451\u0442\u0440 \u0410\u043b\u0435\u043a\u0441\u0435\u0435\u0432\u0438\u0447 \u041f\u043e\u0440\u043e\u0448\u0435\u043d\u043a\u043e (\u041f\u0440\u0435\u0437\u0438\u0434\u0435\u043d\u0442)", "link_text": "\u041f\u0451\u0442\u0440 \u0410\u043b\u0435\u043a\u0441\u0435\u0435\u0432\u0438\u0447 \u041f\u043e\u0440\u043e\u0448\u0435\u043d\u043a\u043e", "search_request": "\u041f\u0451\u0442\u0440 \u0410\u043b\u0435\u043a\u0441\u0435\u0435\u0432\u0438\u0447 \u041f\u043e\u0440\u043e\u0448\u0435\u043d\u043a\u043e", "_source_code": 1, "id": "ruw210553"}, {"entref": "0oCgpydXczMDYzMjMzGALlkzeD", "text": "\u0412\u043b\u0430\u0434\u0438\u043c\u0438\u0440 \u0411\u043e\u0440\u0438\u0441\u043e\u0432\u0438\u0447 \u0413\u0440\u043e\u0439\u0441\u043c\u0430\u043d (\u041f\u0440\u0435\u043c\u044c\u0435\u0440-\u043c\u0438\u043d\u0438\u0441\u0442\u0440)", "link_text": "\u0412\u043b\u0430\u0434\u0438\u043c\u0438\u0440 \u0411\u043e\u0440\u0438\u0441\u043e\u0432\u0438\u0447 \u0413\u0440\u043e\u0439\u0441\u043c\u0430\u043d", "search_request": "\u0412\u043b\u0430\u0434\u0438\u043c\u0438\u0440 \u0411\u043e\u0440\u0438\u0441\u043e\u0432\u0438\u0447 \u0413\u0440\u043e\u0439\u0441\u043c\u0430\u043d", "_source_code": 1, "id": "ruw3063233"}]}]}, "isRuntimeAlias": "1", "restrict_wikifact": true, "type": "entity-fact"}
