{
    "punctuation": [
        "_",
        "-",
        "!",
        "'",
        "(",
        ")",
        ",",
        ".",
        ":",
        ";",
        "?",
        " ",
        "\""
    ],
    "phonemes": [
        "g",
        "i",
        "nn",
        "ii",
        "l",
        "b",
        "kk",
        "mm",
        "h",
        "uu",
        "vv",
        "s",
        "yy",
        "zz",
        "tt",
        "e",
        "pp",
        "j",
        "a",
        "ss",
        "m",
        "p",
        "ch",
        "n",
        "zh",
        "k",
        "ee",
        "r",
        "f",
        "oo",
        "ff",
        "y",
        "t",
        "gg",
        "sch",
        "aa",
        "u",
        "dd",
        "schwa",
        "c",
        "hh",
        "bb",
        "sh",
        "rr",
        "z",
        "d",
        "ll",
        "v"
    ],
    "token_to_id": {
        "_": 1,
        "-": 2,
        "!": 3,
        "'": 4,
        "(": 5,
        ")": 6,
        ",": 7,
        ".": 8,
        ":": 9,
        ";": 10,
        "?": 11,
        " ": 12,
        "\"": 13,
        "g": 14,
        "i": 15,
        "nn": 16,
        "ii": 17,
        "l": 18,
        "b": 19,
        "kk": 20,
        "mm": 21,
        "h": 22,
        "uu": 23,
        "vv": 24,
        "s": 25,
        "yy": 26,
        "zz": 27,
        "tt": 28,
        "e": 29,
        "pp": 30,
        "j": 31,
        "a": 32,
        "ss": 33,
        "m": 34,
        "p": 35,
        "ch": 36,
        "n": 37,
        "zh": 38,
        "k": 39,
        "ee": 40,
        "r": 41,
        "f": 42,
        "oo": 43,
        "ff": 44,
        "y": 45,
        "t": 46,
        "gg": 47,
        "sch": 48,
        "aa": 49,
        "u": 50,
        "dd": 51,
        "schwa": 52,
        "c": 53,
        "hh": 54,
        "bb": 55,
        "sh": 56,
        "rr": 57,
        "z": 58,
        "d": 59,
        "ll": 60,
        "v": 61,
        "SIL1": 62,
        "SIL2": 63,
        "SIL3": 64,
        "SIL4": 65,
        "SIL5": 66,
        "BOS": 67,
        "EOS": 68,
        "SILENCE": 69
    },
    "speakers": {
        "alexr_male": {
            "id": 1
        },
        "anton_samokhvalov_male": {
            "id": 2
        },
        "elena_female": {
            "id": 3
        },
        "ermil_male": {
            "id": 4
        },
        "irina_female": {
            "id": 5
        },
        "jane_female": {
            "id": 6
        },
        "kolya_male": {
            "id": 7
        },
        "kostya_male": {
            "id": 8
        },
        "krosh_male": {
            "id": 9
        },
        "levitan_male": {
            "id": 10
        },
        "nastya_female": {
            "id": 11
        },
        "oksana_female": {
            "id": 12
        },
        "omazh_female": {
            "id": 13
        },
        "sasha_female": {
            "id": 14
        },
        "shitova_female": {
            "id": 15
        },
        "tatyana_abramova_female": {
            "id": 16
        },
        "valtz_male": {
            "id": 17
        },
        "zahar_male": {
            "id": 18
        },
        "elena_mtt_female": {
            "id": 19
        },
        "klukvin_male": {
            "id": 20
        },
        "anastasia_female": {
            "id": 21
        },
        "kuznetsov_male": {
            "id": 22
        },
        "karina_female": {
            "id": 23
        },
        "sergey_fromtech_male": {
            "id": 24
        },
        "b1gdpi44lcd4a37vi6ir": {
            "id": 25
        },
        "irina_ats_female": {
            "id": 25
        },
        "b1gigb8f86bckoo8orfr": {
            "id": 26
        },
        "b1gnh2rh685l4md995np": {
            "id": 27
        },
        "b1gap4l873nc1adftqnu": {
            "id": 28
        },
        "b1g0m97ms7ueh800h4k7": {
            "id": 29
        },
        "b1gvt2nubho67sa74uqh": {
            "id": 30
        },
        "b1g2qbdnpubj52lfa73c": {
            "id": 31
        },
        "b1gs9a5ant07jps2s9d8": {
            "id": 32
        },
        "b1g4atvsitpj2411v2nc": {
            "id": 33
        },
        "b1gut1sktc34pv9nsq35": {
            "id": 34
        },
        "b1gsj4dkfropunv28kq3": {
            "id": 35
        },
        "b1gn60qme365p71ffbns": {
            "id": 36
        },
        "b1gmtkh8sims0j4rluun": {
            "id": 37
        },
        "b1ghd51pmismslrjmelr": {
            "id": 38
        },
        "b1govp35pgjjmbb36pmm": {
            "id": 39
        },
        "b1g0gu61j6fvcih43l9l": {
            "id": 40
        }
    },
    "embeddings": "acoustic_model/embeddings.npz"
}
