{
    "model": "tts_features_extractor",
    "window_size": 256,
    "padding_size": 512,
    "mel_dim": 80,
    "wait_in_queue_limit_ms": 0,
    "engine_path": "features_extractor/features_extractor.trt",
    "profiles": [
        {
            "inputs": {
                "audio": {
                    "min": [
                        1,
                        2205
                    ],
                    "optim": [
                        1,
                        165375
                    ],
                    "max": [
                        1,
                        705600
                    ]
                }
            }
        }
    ],
    "lanes": [
        {
            "batch_size": 1,
            "group_key": 110250,
            "optimization_profile": 0
        },
        {
            "batch_size": 1,
            "group_key": 165375,
            "optimization_profile": 0
        },
        {
            "batch_size": 1,
            "group_key": 264600,
            "optimization_profile": 0
        },
        {
            "batch_size": 1,
            "group_key": 705600,
            "optimization_profile": 0
        }
    ]
}
