{
  "meta": {
    "version": "biovitrum-cloud-resources-{revision}",
    "maintainer": "Ermilov Anton <eranik@yandex-team.ru>",
    "name": "stt-server",
    "description": "ASR server resources"
  },
  "build": {
    "targets" : [
      "cloud/ai/selfhost/docker/stt-server/biovitrum_cloud_e2e",
      "cloud/ai/selfhost/docker/stt-server/normalizer"
    ]
  },
  "data": [
    {
      "source": {
        "path": "cloud/ai/selfhost/docker/stt-server/biovitrum_cloud_e2e",
        "type": "BUILD_OUTPUT"
      },
      "destination": {
        "path": "/lingware"
      }
    },
    {
      "source": {
        "path": "cloud/ai/selfhost/docker/stt-server/normalizer/normalizer.tar.gz",
        "type": "BUILD_OUTPUT",
        "untar": true
      },
      "destination": {
        "path": "/lingware/"
      }
    }
  ]
}
